MANIFEST.in
setup.py
axiome/__init__.py
axiome/axiome.py
axiome/modules.py
axiome/ui.py
axiome/utils.py
axiome.egg-info/PKG-INFO
axiome.egg-info/SOURCES.txt
axiome.egg-info/dependency_links.txt
axiome.egg-info/entry_points.txt
axiome.egg-info/not-zip-safe
axiome.egg-info/requires.txt
axiome.egg-info/top_level.txt
axiome/res/modules
axiome/res/sample
axiome/res/modules/master.xml
axiome/res/modules/alignment/qiime_infernal.xml
axiome/res/modules/alignment/qiime_muscle.xml
axiome/res/modules/alignment/qiime_pynast.xml
axiome/res/modules/chimera/uchime_denovo.xml
axiome/res/modules/classification/qiime_blast.xml
axiome/res/modules/classification/qiime_rdp.xml
axiome/res/modules/classification/qiime_uclust.xml
axiome/res/modules/cluster/cdhit.xml
axiome/res/modules/cluster/qiime_blast.xml
axiome/res/modules/cluster/qiime_cdhit.xml
axiome/res/modules/cluster/qiime_uclust.xml
axiome/res/modules/cluster/uparse.xml
axiome/res/modules/convert_otu_table/full_biom_to_tab.xml
axiome/res/modules/convert_otu_table/rarefied_biom_to_tab.xml
axiome/res/modules/create_otu_table/qiime.xml
axiome/res/modules/mapping/copy.xml
axiome/res/modules/merge_sources/concatenate.xml
axiome/res/modules/misc_analysis/qiime_alpha_rarefaction.xml
axiome/res/modules/misc_analysis/qiime_taxaplot.xml
axiome/res/modules/phylogeny/fasttree.xml
axiome/res/modules/phylogeny/fasttreemp.xml
axiome/res/modules/phylogeny/qiime_clustalw.xml
axiome/res/modules/phylogeny/qiime_fasttree.xml
axiome/res/modules/rarefied_analysis/mesas_indicator-species.xml
axiome/res/modules/rarefied_analysis/mesas_nmds.xml
axiome/res/modules/rarefied_analysis/mesas_pcoa.xml
axiome/res/modules/rarefied_analysis/qiime_2d-pcoa.xml
axiome/res/modules/rarefied_analysis/qiime_compare-sample-groups.xml
axiome/res/modules/rarefied_analysis/qiime_unifrac-pcoa.xml
axiome/res/modules/rarefy_otu_table/qiime.xml
axiome/res/modules/rep_set/qiime.xml
axiome/res/modules/rep_set/uparse.xml
axiome/res/modules/source/fasta.xml
axiome/res/modules/source/pandaseq.xml
axiome/res/sample/hmmb.fasta
axiome/res/sample/metadata_mapping.tsv
axiome/res/sample/sample.ax
axiome/res/sample/sample_file_mapping.tsv