Metadata-Version: 1.1
Name: axiome
Version: 2.0.4
Summary: AXIOME2: Automation Extension and Integration of Microbial Ecology
Home-page: https://github.com/neufeld/AXIOME2
Author: Michael Hall
Author-email: hallm2533@gmail.com
License: MIT
Platform: UNKNOWN
Classifier: Development Status :: 4 - Beta
Classifier: Environment :: Console
Classifier: Intended Audience :: Science/Research
Classifier: License :: OSI Approved :: MIT License
Classifier: Natural Language :: English
Classifier: Operating System :: POSIX :: Linux
Classifier: Topic :: Scientific/Engineering :: Bio-Informatics
